{"mode":"ml_sim","selected_by":"end_equity","scenario":{"name":"qqq_cross_off","symbols":["SPY","QQQ"],"trade_symbol":"QQQ","cross_symbol":"SPY","include_cross":false},"summary_path":"C:\\dev\\Coding\\Trading Bot\\adaptive-systematic-trading\\step2_out\\selection\\qqq_cross_off\\step2b_summary.json","trial":{"filter_name":"no_overnight","knobs":{"trend_fast_span":8,"trend_slow_span":56,"trend_in":0.779159,"pullback_z":1.472738,"trend_regime_min":0.463816,"min_event_spacing_bars":1,"ewma_var_alpha":0.098537,"atr_span":10,"horizon_intra":14,"horizon_overn":14,"tp_mult_intra":2.70049,"sl_mult_intra":1.128114,"tp_mult_overn":2.925683,"sl_mult_overn":1.276433,"same_bar_policy":"worst","spread_half_bps":{"SPY":0.8,"QQQ":1.2,"SMH":1.8},"slip_base_bps":0.8,"slip_vol_mult":0.05,"slip_spike_add_bps":2.0,"vol_spike_q":0.9,"overnight_slip_add_bps":1.5,"commission_round_trip_bps":1.0,"gap_lookback_events":120,"gap_tail_k":2.0,"sigma_rank_window":500,"atr_rank_window":500,"rank_min_periods":200,"intraday_tail_window":200,"intraday_tail_min_periods":50,"intraday_tail_z":2.0,"include_cross_asset":false,"cross_symbol":"SPY","cross_merge_tolerance":"30min","dropna_core_only":true},"n_bars":17626,"split_bar_idx":14100,"split_time_utc":"2024-02-06 19:00:00+00:00","base_counts":{"all_events":10062,"filtered_events":8611,"train_filtered":6914,"test_filtered":1691},"no_ml":{"train":{"n":913,"y_rate":0.41402,"net_bps_mean":0.258891,"net_bps_med":-26.457385,"cum_logret":0.023637,"end_equity":10239.182688,"max_drawdown":0.265528,"cagr":0.002947},"test":{"n":217,"y_rate":0.396313,"net_bps_mean":-4.87345,"net_bps_med":-31.84647,"cum_logret":-0.105754,"end_equity":8996.460552,"max_drawdown":0.162594,"cagr":-0.051808},"score":7328.398739},"ml_sim":{"model_features":["trend_score","pullback_z","sigma","u_atr","sigma_prank","u_atr_prank","gap_sd","gap_tail","vol_z","dist_to_hi","range_ratio","tp_to_cost","entry_overnight"],"p_cut":0.552617,"edge_cut":0.002369,"p_quantile":0.65,"edge_quantile":0.6,"threshold_tune_score":-58.190823,"target_keep_train":80,"ret_mix_weight":0.35,"valid":true,"train":{"n":276,"y_rate":0.442029,"net_bps_mean":6.655081,"net_bps_med":-23.644244,"cum_logret":0.18368,"end_equity":12016.315361,"max_drawdown":0.119533,"cagr":0.023371},"test":{"n":108,"y_rate":0.453704,"net_bps_mean":8.777201,"net_bps_med":-22.637418,"cum_logret":0.094794,"end_equity":10994.320983,"max_drawdown":0.053714,"cagr":0.049827},"score":10318.889622},"trial":1},"test_snapshot":{"n":108,"end_equity":10994.320983,"cagr":0.049827,"max_drawdown":0.053714,"calmar":0.927635,"net_bps_mean":8.777201}}